{
  "project_name": "IMDb Movie Review Sentiment Analysis using Simple RNN",
  "artifact_format": "Keras v3 .keras",
  "training_source": "TensorFlow/Keras IMDb dataset subset exported by the supplied notebook",
  "training_pool_reviews": 2000,
  "model_fit_reviews": 1600,
  "validation_reviews": 400,
  "test_reviews": 600,
  "model_selection_split": "80/20 stratified split within the 2,000-review training pool",
  "post_selection_refit": false,
  "reproducibility_note": "The saved early-stopped model and tokenizer correspond to the model-fitting partition; the final test set was untouched.",
  "vocabulary_size": 7907,
  "max_vocabulary": 10000,
  "chunk_length": 80,
  "chunk_stride": 60,
  "max_chunks_per_review": 6,
  "embedding_dimension": 80,
  "simple_rnn_units": 48,
  "dense_units": 32,
  "dropout": 0.3,
  "prediction_aggregation": "mean positive probability across review chunks",
  "decision_threshold": 0.43,
  "threshold_selection": "F1-maximizing threshold selected on the 400-review validation partition before untouched test evaluation",
  "baseline_comparison_scope": "TF-IDF baseline trained on the same 1,600-review model-fitting partition as the Simple RNN",
  "test_metrics": {
    "model": "Simple RNN",
    "threshold": 0.43,
    "accuracy": 0.7433333333333333,
    "balanced_accuracy": 0.7440330681363616,
    "precision": 0.6988950276243094,
    "recall": 0.8489932885906041,
    "f1": 0.7666666666666667,
    "specificity": 0.6390728476821192,
    "roc_auc": 0.8201031156940308,
    "pr_auc": 0.799235807145052,
    "mcc": 0.4988242009689806,
    "test_rows": 600,
    "tn": 193,
    "fp": 109,
    "fn": 45,
    "tp": 253
  },
  "baseline_metrics": {
    "model": "TF-IDF + Logistic Regression",
    "threshold": 0.5,
    "test_rows": 600,
    "accuracy": 0.845,
    "balanced_accuracy": 0.8451820080892484,
    "precision": 0.8253968253968254,
    "recall": 0.87248322147651,
    "f1": 0.8482871125611745,
    "specificity": 0.8178807947019867,
    "roc_auc": 0.9322969909773767,
    "pr_auc": 0.93385377262666,
    "mcc": 0.6912132318116223,
    "tn": 247,
    "fp": 55,
    "fn": 38,
    "tp": 260
  },
  "majority_metrics": {
    "model": "Majority Class",
    "predicted_class": 1,
    "threshold": 0.5,
    "test_rows": 600,
    "accuracy": 0.49666666666666665,
    "balanced_accuracy": 0.5,
    "precision": 0.49666666666666665,
    "recall": 1.0,
    "f1": 0.6636971046770601,
    "specificity": 0.0,
    "roc_auc": 0.5,
    "pr_auc": 0.49666666666666665,
    "mcc": 0.0,
    "tn": 0,
    "fp": 302,
    "fn": 0,
    "tp": 298
  },
  "random_seed": 42
}